{
  "mappings": {
    "user": {
      "properties": {
        "username": {
          "type": "text"
        },
        "image": {
          "type": "text"
        },
        "email": {
          "type": "text"
        },
        "password": {
          "type": "text"
        },
        "bio": {
          "type": "text"
        },
        "postsLike": {
          "type": "integer"
        },
        "friends": {
          "properties": {
            "username": {
              "type": "text"
            },
            "id": {
              "type": "text"
            }
          }
        }
      }
    }
  }
}
